{
  "type": "Feature",
  "properties": {
    "gn:admin1_code":"16.0",
    "gn:asciiname":"Mapkinkin",
    "gn:country_code":"VU",
    "gn:dem":108,
    "gn:feature_class":"P",
    "gn:feature_code":"PPL",
    "gn:name":"Mapkinkin",
    "gn:population":0,
    "gn:timezone":"Pacific/Efate",
    "iso:country":"VU",
    "wof:name":"Mapkinkin",
    "wof:placetype":"locality"
},
  "geometry": {"coordinates":[167.98333,-16.28333],"type":"Point"}
}