{
  "type": "Feature",
  "properties": {
    "gn:admin1_code":"13.0",
    "gn:asciiname":"Lewelvaru",
    "gn:country_code":"VU",
    "gn:dem":248,
    "gn:feature_class":"P",
    "gn:feature_code":"PPL",
    "gn:name":"Lewelvaru",
    "gn:population":0,
    "gn:timezone":"Pacific/Efate",
    "iso:country":"VU",
    "wof:name":"Lewelvaru",
    "wof:placetype":"locality"
},
  "geometry": {"coordinates":[167.05000000000001,-15.06667],"type":"Point"}
}