{
  "type": "Feature",
  "properties": {
    "gn:admin1_code":"15.0",
    "gn:asciiname":"Oumetch",
    "gn:country_code":"VU",
    "gn:dem":9,
    "gn:feature_class":"P",
    "gn:feature_code":"PPL",
    "gn:name":"Oumetch",
    "gn:population":0,
    "gn:timezone":"Pacific/Efate",
    "iso:country":"VU",
    "name:und_x_variant":[
        "Umetch"
    ],
    "wof:name":"Oumetch",
    "wof:placetype":"locality"
},
  "geometry": {"coordinates":[169.85181,-20.24678],"type":"Point"}
}