{
  "type": "Feature",
  "properties": {
    "gn:admin1_code":"13.0",
    "gn:asciiname":"Weilberi",
    "gn:country_code":"VU",
    "gn:dem":229,
    "gn:feature_class":"P",
    "gn:feature_code":"PPL",
    "gn:name":"W\u00e9ilb\u00e9ri",
    "gn:population":0,
    "gn:timezone":"Pacific/Efate",
    "iso:country":"VU",
    "wof:name":"Weilberi",
    "wof:placetype":"locality"
},
  "geometry": {"coordinates":[167.01667,-15.08333],"type":"Point"}
}