{
  "type": "Feature",
  "properties": {
    "gn:admin1_code":"17.0",
    "gn:asciiname":"Napila",
    "gn:country_code":"VU",
    "gn:dem":393,
    "gn:feature_class":"P",
    "gn:feature_code":"PPL",
    "gn:name":"Napila",
    "gn:population":0,
    "gn:timezone":"Pacific/Efate",
    "iso:country":"VU",
    "wof:name":"Napila",
    "wof:placetype":"locality"
},
  "geometry": {"coordinates":[167.81666999999999,-15.45],"type":"Point"}
}