{
  "type": "Feature",
  "properties": {
    "gn:admin1_code":"13.0",
    "gn:asciiname":"Tonvar",
    "gn:country_code":"VU",
    "gn:dem":646,
    "gn:feature_class":"P",
    "gn:feature_code":"PPL",
    "gn:name":"Tonvar",
    "gn:population":0,
    "gn:timezone":"Pacific/Efate",
    "iso:country":"VU",
    "wof:name":"Tonvar",
    "wof:placetype":"locality"
},
  "geometry": {"coordinates":[166.90000000000001,-15.41667],"type":"Point"}
}