{
  "type": "Feature",
  "properties": {
    "gn:admin1_code":"18.0",
    "gn:asciiname":"Pourao",
    "gn:country_code":"VU",
    "gn:dem":172,
    "gn:feature_class":"P",
    "gn:feature_code":"PPL",
    "gn:name":"Pourao",
    "gn:population":0,
    "gn:timezone":"Pacific/Efate",
    "iso:country":"VU",
    "wof:name":"Pourao",
    "wof:placetype":"locality"
},
  "geometry": {"coordinates":[168.55000000000001,-16.88332999999999],"type":"Point"}
}