{
  "type": "Feature",
  "properties": {
    "gn:asciiname":"Demsal",
    "gn:country_code":"VU",
    "gn:dem":245,
    "gn:feature_class":"P",
    "gn:feature_code":"PPL",
    "gn:name":"Demsal",
    "gn:population":0,
    "gn:timezone":"Pacific/Efate",
    "iso:country":"VU",
    "wof:name":"Demsal",
    "wof:placetype":"locality"
},
  "geometry": {"coordinates":[169.05466000000001,-18.89354],"type":"Point"}
}