{
  "type": "Feature",
  "properties": {
    "gn:asciiname":"Saint Lawrence",
    "gn:country_code":"VU",
    "gn:dem":10,
    "gn:feature_class":"P",
    "gn:feature_code":"PPL",
    "gn:name":"Saint Lawrence",
    "gn:population":0,
    "gn:timezone":"Pacific/Efate",
    "iso:country":"VU",
    "wof:name":"Saint Lawrence",
    "wof:placetype":"locality"
},
  "geometry": {"coordinates":[168.33002999999999,-17.53782],"type":"Point"}
}