{
  "type": "Feature",
  "properties": {
    "gn:admin1_code":"17.0",
    "gn:asciiname":"Nevor",
    "gn:country_code":"VU",
    "gn:dem":64,
    "gn:feature_class":"P",
    "gn:feature_code":"PPL",
    "gn:name":"Nevor",
    "gn:population":0,
    "gn:timezone":"Pacific/Efate",
    "iso:country":"VU",
    "wof:name":"Nevor",
    "wof:placetype":"locality"
},
  "geometry": {"coordinates":[168.17426,-15.84458],"type":"Point"}
}