{
  "type": "Feature",
  "properties": {
    "gn:admin1_code":"17.0",
    "gn:asciiname":"Level",
    "gn:country_code":"VU",
    "gn:dem":397,
    "gn:feature_class":"P",
    "gn:feature_code":"PPL",
    "gn:name":"L\u00e9vel",
    "gn:population":0,
    "gn:timezone":"Pacific/Efate",
    "iso:country":"VU",
    "name:cat_x_preferred":[
        "Nivell"
    ],
    "name:ces_x_preferred":[
        "Level"
    ],
    "name:deu_x_preferred":[
        "Level"
    ],
    "name:epo_x_preferred":[
        "Nivelo"
    ],
    "name:est_x_preferred":[
        "Level"
    ],
    "name:fra_x_preferred":[
        "Level"
    ],
    "name:ita_x_preferred":[
        "Livello"
    ],
    "name:jpn_x_preferred":[
        "\u30ec\u30d9\u30eb"
    ],
    "name:lav_x_preferred":[
        "L\u012bmenis"
    ],
    "name:por_x_preferred":[
        "N\u00edvel"
    ],
    "name:rus_x_preferred":[
        "\u0423\u0440\u043e\u0432\u0435\u043d\u044c"
    ],
    "name:slk_x_preferred":[
        "Level"
    ],
    "name:spa_x_preferred":[
        "Nivel"
    ],
    "name:srp_x_preferred":[
        "Livello"
    ],
    "name:swe_x_preferred":[
        "Level"
    ],
    "name:tur_x_preferred":[
        "Level"
    ],
    "name:ukr_x_preferred":[
        "\u0420\u0456\u0432\u0435\u043d\u044c"
    ],
    "wof:name":"Level",
    "wof:placetype":"locality"
},
  "geometry": {"coordinates":[168.16666999999995,-15.68333],"type":"Point"}
}