{
  "type": "Feature",
  "properties": {
    "gn:admin1_code":"16.0",
    "gn:asciiname":"Larevet",
    "gn:country_code":"VU",
    "gn:dem":-9999,
    "gn:feature_class":"P",
    "gn:feature_code":"PPL",
    "gn:name":"Lar\u00e9vet",
    "gn:population":0,
    "gn:timezone":"Pacific/Efate",
    "iso:country":"VU",
    "name:und_x_variant":[
        "Laraw\u00e8t",
        "Laravet",
        "Lar\u00e9vet",
        "Larav\u00e9t"
    ],
    "wof:name":"Larevet",
    "wof:placetype":"locality"
},
  "geometry": {"coordinates":[167.34999999999999,-16.18333],"type":"Point"}
}