{
  "type": "Feature",
  "properties": {
    "gn:admin1_code":"15.0",
    "gn:asciiname":"Lenapouas",
    "gn:country_code":"VU",
    "gn:dem":318,
    "gn:feature_class":"P",
    "gn:feature_code":"PPL",
    "gn:name":"L\u00e9napouas",
    "gn:population":0,
    "gn:timezone":"Pacific/Efate",
    "iso:country":"VU",
    "wof:name":"Lenapouas",
    "wof:placetype":"locality"
},
  "geometry": {"coordinates":[169.31666999999999,-19.51667],"type":"Point"}
}