{
  "type": "Feature",
  "properties": {
    "gn:admin1_code":"15.0",
    "gn:asciiname":"Loounaoula",
    "gn:country_code":"VU",
    "gn:dem":327,
    "gn:feature_class":"P",
    "gn:feature_code":"PPL",
    "gn:name":"Loounaoula",
    "gn:population":0,
    "gn:timezone":"Pacific/Efate",
    "iso:country":"VU",
    "wof:name":"Loounaoula",
    "wof:placetype":"locality"
},
  "geometry": {"coordinates":[169.30000000000001,-19.43333],"type":"Point"}
}