{
  "type": "Feature",
  "properties": {
    "gn:admin1_code":"16.0",
    "gn:asciiname":"Ranwilinto",
    "gn:country_code":"VU",
    "gn:dem":278,
    "gn:feature_class":"P",
    "gn:feature_code":"PPL",
    "gn:name":"Ranwilinto",
    "gn:population":0,
    "gn:timezone":"Pacific/Efate",
    "iso:country":"VU",
    "wof:name":"Ranwilinto",
    "wof:placetype":"locality"
},
  "geometry": {"coordinates":[168.09999999999999,-16.18333],"type":"Point"}
}