{
  "type": "Feature",
  "properties": {
    "gn:admin1_code":"13.0",
    "gn:asciiname":"Porao",
    "gn:country_code":"VU",
    "gn:dem":169,
    "gn:feature_class":"P",
    "gn:feature_code":"PPL",
    "gn:name":"Porao",
    "gn:population":0,
    "gn:timezone":"Pacific/Efate",
    "iso:country":"VU",
    "wof:name":"Porao",
    "wof:placetype":"locality"
},
  "geometry": {"coordinates":[166.63333,-14.68333],"type":"Point"}
}