{
  "type": "Feature",
  "properties": {
    "gn:admin1_code":"15.0",
    "gn:asciiname":"Rampounisia",
    "gn:country_code":"VU",
    "gn:dem":283,
    "gn:feature_class":"P",
    "gn:feature_code":"PPL",
    "gn:name":"Rampounisia",
    "gn:population":0,
    "gn:timezone":"Pacific/Efate",
    "iso:country":"VU",
    "wof:name":"Rampounisia",
    "wof:placetype":"locality"
},
  "geometry": {"coordinates":[169.20237,-18.95325],"type":"Point"}
}