{
  "type": "Feature",
  "properties": {
    "gn:admin1_code":"16.0",
    "gn:asciiname":"Matenoua",
    "gn:country_code":"VU",
    "gn:dem":15,
    "gn:feature_class":"P",
    "gn:feature_code":"PPL",
    "gn:name":"Mat\u00e9noua",
    "gn:population":0,
    "gn:timezone":"Pacific/Efate",
    "iso:country":"VU",
    "wof:name":"Matenoua",
    "wof:placetype":"locality"
},
  "geometry": {"coordinates":[167.61667,-16.25],"type":"Point"}
}