{
  "type": "Feature",
  "properties": {
    "gn:admin1_code":"17.0",
    "gn:asciiname":"Saltas",
    "gn:country_code":"VU",
    "gn:dem":176,
    "gn:feature_class":"P",
    "gn:feature_code":"PPL",
    "gn:name":"Saltas",
    "gn:population":0,
    "gn:timezone":"Pacific/Efate",
    "iso:country":"VU",
    "wof:name":"Saltas",
    "wof:placetype":"locality"
},
  "geometry": {"coordinates":[168.25,-15.98333],"type":"Point"}
}