{
  "type": "Feature",
  "properties": {
    "gn:admin1_code":"15.0",
    "gn:asciiname":"Ikounap",
    "gn:country_code":"VU",
    "gn:dem":415,
    "gn:feature_class":"P",
    "gn:feature_code":"PPL",
    "gn:name":"Ikounap",
    "gn:population":0,
    "gn:timezone":"Pacific/Efate",
    "iso:country":"VU",
    "wof:name":"Ikounap",
    "wof:placetype":"locality"
},
  "geometry": {"coordinates":[169.38333,-19.53333],"type":"Point"}
}