{
  "type": "Feature",
  "properties": {
    "gn:admin1_code":"18.0",
    "gn:asciiname":"Bonkowia",
    "gn:country_code":"VU",
    "gn:dem":49,
    "gn:feature_class":"P",
    "gn:feature_code":"PPL",
    "gn:name":"Bonkowia",
    "gn:population":0,
    "gn:timezone":"Pacific/Efate",
    "iso:country":"VU",
    "name:und_x_variant":[
        "Bonkovia"
    ],
    "wof:name":"Bonkowia",
    "wof:placetype":"locality"
},
  "geometry": {"coordinates":[168.13333,-16.66667],"type":"Point"}
}