{
  "type": "Feature",
  "properties": {
    "gn:admin1_code":"16.0",
    "gn:asciiname":"Lampetiar",
    "gn:country_code":"VU",
    "gn:dem":21,
    "gn:feature_class":"P",
    "gn:feature_code":"PPL",
    "gn:name":"Lamp\u00e9tiar",
    "gn:population":0,
    "gn:timezone":"Pacific/Efate",
    "iso:country":"VU",
    "wof:name":"Lampetiar",
    "wof:placetype":"locality"
},
  "geometry": {"coordinates":[167.23333,-15.88333],"type":"Point"}
}