{
  "type": "Feature",
  "properties": {
    "gn:admin1_code":"14.0",
    "gn:asciiname":"Nasanga",
    "gn:country_code":"VU",
    "gn:dem":14,
    "gn:feature_class":"P",
    "gn:feature_code":"PPL",
    "gn:name":"Nasanga",
    "gn:population":0,
    "gn:timezone":"Pacific/Efate",
    "iso:country":"VU",
    "wof:name":"Nasanga",
    "wof:placetype":"locality"
},
  "geometry": {"coordinates":[168.42908,-17.25763],"type":"Point"}
}