{
  "type": "Feature",
  "properties": {
    "gn:admin1_code":"17.0",
    "gn:asciiname":"Matbopo",
    "gn:country_code":"VU",
    "gn:dem":312,
    "gn:feature_class":"P",
    "gn:feature_code":"PPL",
    "gn:name":"Matbopo",
    "gn:population":0,
    "gn:timezone":"Pacific/Efate",
    "iso:country":"VU",
    "wof:name":"Matbopo",
    "wof:placetype":"locality"
},
  "geometry": {"coordinates":[168.16666999999995,-15.53333],"type":"Point"}
}