{
  "type": "Feature",
  "properties": {
    "gn:admin1_code":"16.0",
    "gn:asciiname":"Retour",
    "gn:country_code":"VU",
    "gn:dem":211,
    "gn:feature_class":"P",
    "gn:feature_code":"PPL",
    "gn:name":"R\u00e9tour",
    "gn:population":0,
    "gn:timezone":"Pacific/Efate",
    "iso:country":"VU",
    "wof:name":"Retour",
    "wof:placetype":"locality"
},
  "geometry": {"coordinates":[167.76667,-16.36667000000001],"type":"Point"}
}