{
  "type": "Feature",
  "properties": {
    "gn:admin1_code":"13.0",
    "gn:asciiname":"Koulouwan",
    "gn:country_code":"VU",
    "gn:dem":1112,
    "gn:feature_class":"P",
    "gn:feature_code":"PPL",
    "gn:name":"Koulouwan",
    "gn:population":0,
    "gn:timezone":"Pacific/Efate",
    "iso:country":"VU",
    "wof:name":"Koulouwan",
    "wof:placetype":"locality"
},
  "geometry": {"coordinates":[166.81666999999999,-15.46667],"type":"Point"}
}