{
  "type": "Feature",
  "properties": {
    "gn:admin1_code":"18.0",
    "gn:asciiname":"Mele",
    "gn:country_code":"VU",
    "gn:dem":16,
    "gn:feature_class":"P",
    "gn:feature_code":"PPL",
    "gn:name":"Mele",
    "gn:population":0,
    "gn:timezone":"Pacific/Efate",
    "iso:country":"VU",
    "name:fra_x_preferred":[
        "M\u00e9l\u00e9"
    ],
    "wof:name":"Mele",
    "wof:placetype":"locality"
},
  "geometry": {"coordinates":[168.28995,-17.68925],"type":"Point"}
}