{
  "type": "Feature",
  "properties": {
    "gn:admin1_code":"7.0",
    "gn:asciiname":"Wasaka",
    "gn:country_code":"VU",
    "gn:dem":-9999,
    "gn:feature_class":"P",
    "gn:feature_code":"PPL",
    "gn:name":"Wasaka",
    "gn:population":0,
    "gn:timezone":"Pacific/Efate",
    "iso:country":"VU",
    "name:fra_x_preferred":[
        "Wasaka"
    ],
    "wof:name":"Wasaka",
    "wof:placetype":"locality"
},
  "geometry": {"coordinates":[167.44999999999999,-13.96667],"type":"Point"}
}