{
  "type": "Feature",
  "properties": {
    "gn:admin1_code":"7.0",
    "gn:asciiname":"Avay (Var)",
    "gn:country_code":"VU",
    "gn:dem":19,
    "gn:feature_class":"P",
    "gn:feature_code":"PPL",
    "gn:name":"Avay (Var)",
    "gn:population":0,
    "gn:timezone":"Pacific/Efate",
    "iso:country":"VU",
    "wof:name":"Avay (Var)",
    "wof:placetype":"locality"
},
  "geometry": {"coordinates":[167.63468,-13.70128],"type":"Point"}
}