{
  "type": "Feature",
  "properties": {
    "gn:admin1_code":"18.0",
    "gn:asciiname":"Stade",
    "gn:country_code":"VU",
    "gn:dem":-9999,
    "gn:feature_class":"P",
    "gn:feature_code":"PPL",
    "gn:name":"Stade",
    "gn:population":0,
    "gn:timezone":"Pacific/Efate",
    "iso:country":"VU",
    "name:ara_x_preferred":[
        "\u0634\u062a\u0627\u062f\u0647"
    ],
    "name:ast_x_preferred":[
        "Stade"
    ],
    "name:azb_x_preferred":[
        "\u0627\u0634\u062a\u062f\u062a\u0647"
    ],
    "name:bel_x_preferred":[
        "\u0428\u0442\u0430\u0434\u044d"
    ],
    "name:bul_x_preferred":[
        "\u0429\u0430\u0434\u0435"
    ],
    "name:cat_x_preferred":[
        "Stade"
    ],
    "name:ceb_x_preferred":[
        "Stade"
    ],
    "name:dan_x_preferred":[
        "Stade"
    ],
    "name:deu_x_preferred":[
        "Stade"
    ],
    "name:epo_x_preferred":[
        "Stade"
    ],
    "name:est_x_preferred":[
        "Stade"
    ],
    "name:eus_x_preferred":[
        "Stade"
    ],
    "name:fas_x_preferred":[
        "\u0627\u0634\u062a\u062f\u062a\u0647"
    ],
    "name:fin_x_preferred":[
        "Stade"
    ],
    "name:fra_x_preferred":[
        "Stade"
    ],
    "name:heb_x_preferred":[
        "\u05e9\u05d8\u05d0\u05d3\u05d4"
    ],
    "name:hun_x_preferred":[
        "Stade"
    ],
    "name:hye_x_preferred":[
        "\u0547\u057f\u0561\u0564\u0565"
    ],
    "name:ind_x_preferred":[
        "Stade"
    ],
    "name:ita_x_preferred":[
        "Stade"
    ],
    "name:jpn_x_preferred":[
        "\u30b7\u30e5\u30bf\u30fc\u30c7"
    ],
    "name:kor_x_preferred":[
        "\uc288\ud0c0\ub370"
    ],
    "name:msa_x_preferred":[
        "Stade"
    ],
    "name:nds_x_preferred":[
        "Gemeen Stood"
    ],
    "name:nld_x_preferred":[
        "Stade"
    ],
    "name:nor_x_preferred":[
        "Stade"
    ],
    "name:pol_x_preferred":[
        "Stade"
    ],
    "name:por_x_preferred":[
        "Stade"
    ],
    "name:ron_x_preferred":[
        "Stade"
    ],
    "name:rus_x_preferred":[
        "\u0428\u0442\u0430\u0434\u0435"
    ],
    "name:slv_x_preferred":[
        "Stade"
    ],
    "name:spa_x_preferred":[
        "Stade"
    ],
    "name:sqi_x_preferred":[
        "Stade"
    ],
    "name:srp_x_preferred":[
        "\u0428\u0442\u0430\u0434\u0435"
    ],
    "name:swe_x_preferred":[
        "Stade"
    ],
    "name:tat_x_preferred":[
        "\u0428\u0442\u0430\u0434\u0435"
    ],
    "name:tur_x_preferred":[
        "Stade"
    ],
    "name:ukr_x_preferred":[
        "\u0428\u0442\u0430\u0434\u0435"
    ],
    "name:uzb_x_preferred":[
        "Stade"
    ],
    "name:vol_x_preferred":[
        "Stade"
    ],
    "name:war_x_preferred":[
        "Stade"
    ],
    "name:zho_x_preferred":[
        "\u65bd\u5854\u5fb7"
    ],
    "wof:name":"Stade",
    "wof:placetype":"locality"
},
  "geometry": {"coordinates":[168.30167,-17.74167000000001],"type":"Point"}
}