{
  "type": "Feature",
  "properties": {
    "gn:admin1_code":"17.0",
    "gn:asciiname":"Alele",
    "gn:country_code":"VU",
    "gn:dem":298,
    "gn:feature_class":"P",
    "gn:feature_code":"PPL",
    "gn:name":"Al\u00e9l\u00e9",
    "gn:population":0,
    "gn:timezone":"Pacific/Efate",
    "iso:country":"VU",
    "name:ceb_x_preferred":[
        "Alele"
    ],
    "name:deu_x_preferred":[
        "Alele"
    ],
    "name:fas_x_preferred":[
        "\u0627\u0644\u06cc\u0644"
    ],
    "name:fra_x_preferred":[
        "Alele"
    ],
    "name:ita_x_preferred":[
        "Alele"
    ],
    "name:pol_x_preferred":[
        "Alele"
    ],
    "name:urd_x_preferred":[
        "\u0627\u0644\u06cc\u0644\u06d2"
    ],
    "wof:name":"Alele",
    "wof:placetype":"locality"
},
  "geometry": {"coordinates":[168.16666999999995,-15.51667],"type":"Point"}
}