{
  "type": "Feature",
  "properties": {
    "gn:admin1_code":"17.0",
    "gn:asciiname":"Alele",
    "gn:country_code":"VU",
    "gn:dem":298,
    "gn:feature_class":"P",
    "gn:feature_code":"PPL",
    "gn:name":"Al\u00e9l\u00e9",
    "gn:population":0,
    "gn:timezone":"Pacific/Efate",
    "iso:country":"VU",
    "wof:name":"Alele",
    "wof:placetype":"locality"
},
  "geometry": {"coordinates":[168.16666999999995,-15.51667],"type":"Point"}
}