{
  "type": "Feature",
  "properties": {
    "gn:admin1_code":"17.0",
    "gn:asciiname":"Nagap",
    "gn:country_code":"VU",
    "gn:dem":47,
    "gn:feature_class":"P",
    "gn:feature_code":"PPL",
    "gn:name":"Nagap",
    "gn:population":0,
    "gn:timezone":"Pacific/Efate",
    "iso:country":"VU",
    "wof:name":"Nagap",
    "wof:placetype":"locality"
},
  "geometry": {"coordinates":[167.96666999999999,-15.31667],"type":"Point"}
}