{
  "type": "Feature",
  "properties": {
    "gn:admin1_code":"17.0",
    "gn:asciiname":"Nazareth-Rantis",
    "gn:country_code":"VU",
    "gn:dem":109,
    "gn:feature_class":"P",
    "gn:feature_code":"PPL",
    "gn:name":"Nazareth-Rantis",
    "gn:population":0,
    "gn:timezone":"Pacific/Efate",
    "iso:country":"VU",
    "wof:name":"Nazareth-Rantis",
    "wof:placetype":"locality"
},
  "geometry": {"coordinates":[168.26667,-15.86667],"type":"Point"}
}