{
  "type": "Feature",
  "properties": {
    "gn:admin1_code":"17.0",
    "gn:asciiname":"Laratava",
    "gn:country_code":"VU",
    "gn:dem":36,
    "gn:feature_class":"P",
    "gn:feature_code":"PPL",
    "gn:name":"Laratava",
    "gn:population":0,
    "gn:timezone":"Pacific/Efate",
    "iso:country":"VU",
    "wof:name":"Laratava",
    "wof:placetype":"locality"
},
  "geometry": {"coordinates":[168.15000000000001,-15.45],"type":"Point"}
}