{
  "type": "Feature",
  "properties": {
    "gn:admin1_code":"18.0",
    "gn:asciiname":"Utanlangi",
    "gn:country_code":"VU",
    "gn:dem":10,
    "gn:feature_class":"P",
    "gn:feature_code":"PPL",
    "gn:name":"Utanlangi",
    "gn:population":0,
    "gn:timezone":"Pacific/Efate",
    "iso:country":"VU",
    "wof:name":"Utanlangi",
    "wof:placetype":"locality"
},
  "geometry": {"coordinates":[168.32221999999999,-17.43333],"type":"Point"}
}