{
  "type": "Feature",
  "properties": {
    "gn:admin1_code":"15.0",
    "gn:asciiname":"Anowounoouras",
    "gn:country_code":"VU",
    "gn:dem":5,
    "gn:feature_class":"P",
    "gn:feature_code":"PPL",
    "gn:name":"Anowounoouras",
    "gn:population":0,
    "gn:timezone":"Pacific/Efate",
    "iso:country":"VU",
    "wof:name":"Anowounoouras",
    "wof:placetype":"locality"
},
  "geometry": {"coordinates":[169.78333000000001,-20.23333],"type":"Point"}
}