{
  "type": "Feature",
  "properties": {
    "gn:admin1_code":"17.0",
    "gn:asciiname":"Lolomatwi",
    "gn:country_code":"VU",
    "gn:dem":276,
    "gn:feature_class":"P",
    "gn:feature_code":"PPL",
    "gn:name":"Lolomatwi",
    "gn:population":0,
    "gn:timezone":"Pacific/Efate",
    "iso:country":"VU",
    "wof:name":"Lolomatwi",
    "wof:placetype":"locality"
},
  "geometry": {"coordinates":[167.80000000000001,-15.33333],"type":"Point"}
}