{
  "type": "Feature",
  "properties": {
    "gn:admin1_code":"17.0",
    "gn:asciiname":"Tosi",
    "gn:country_code":"VU",
    "gn:dem":145,
    "gn:feature_class":"P",
    "gn:feature_code":"PPL",
    "gn:name":"Tosi",
    "gn:population":0,
    "gn:timezone":"Pacific/Efate",
    "iso:country":"VU",
    "wof:name":"Tosi",
    "wof:placetype":"locality"
},
  "geometry": {"coordinates":[168.13333,-15.68333],"type":"Point"}
}