{
  "type": "Feature",
  "properties": {
    "gn:admin1_code":"17.0",
    "gn:asciiname":"Tosi",
    "gn:country_code":"VU",
    "gn:dem":145,
    "gn:feature_class":"P",
    "gn:feature_code":"PPL",
    "gn:name":"Tosi",
    "gn:population":0,
    "gn:timezone":"Pacific/Efate",
    "iso:country":"VU",
    "name:ceb_x_preferred":[
        "Tosi"
    ],
    "name:deu_x_preferred":[
        "Tosi"
    ],
    "name:fin_x_preferred":[
        "Tosi"
    ],
    "name:fra_x_preferred":[
        "Tosi"
    ],
    "name:ita_x_preferred":[
        "Tosi"
    ],
    "name:rus_x_preferred":[
        "\u0422\u043e\u0437\u0438"
    ],
    "name:spa_x_preferred":[
        "Tosi"
    ],
    "name:srp_x_preferred":[
        "Tozi"
    ],
    "name:swe_x_preferred":[
        "Tosi"
    ],
    "wof:name":"Tosi",
    "wof:placetype":"locality"
},
  "geometry": {"coordinates":[168.13333,-15.68333],"type":"Point"}
}