{
  "type": "Feature",
  "properties": {
    "gn:admin1_code":"16.0",
    "gn:asciiname":"Boroumvor",
    "gn:country_code":"VU",
    "gn:dem":27,
    "gn:feature_class":"P",
    "gn:feature_code":"PPL",
    "gn:name":"Boroumvor",
    "gn:population":0,
    "gn:timezone":"Pacific/Efate",
    "iso:country":"VU",
    "wof:name":"Boroumvor",
    "wof:placetype":"locality"
},
  "geometry": {"coordinates":[167.56666999999999,-16.53333],"type":"Point"}
}