{
  "type": "Feature",
  "properties": {
    "gn:admin1_code":"18.0",
    "gn:asciiname":"Bouroumba",
    "gn:country_code":"VU",
    "gn:dem":-9999,
    "gn:feature_class":"P",
    "gn:feature_code":"PPL",
    "gn:name":"Bouroumba",
    "gn:population":0,
    "gn:timezone":"Pacific/Efate",
    "iso:country":"VU",
    "name:und_x_variant":[
        "Bucumba",
        "Burumba",
        "Bouroumba"
    ],
    "wof:name":"Bouroumba",
    "wof:placetype":"locality"
},
  "geometry": {"coordinates":[168.11667,-16.71667],"type":"Point"}
}