{
  "type": "Feature",
  "properties": {
    "gn:admin1_code":"15.0",
    "gn:asciiname":"Ombous",
    "gn:country_code":"VU",
    "gn:dem":50,
    "gn:feature_class":"P",
    "gn:feature_code":"PPL",
    "gn:name":"Ombous",
    "gn:population":0,
    "gn:timezone":"Pacific/Efate",
    "iso:country":"VU",
    "wof:name":"Ombous",
    "wof:placetype":"locality"
},
  "geometry": {"coordinates":[169.46666999999999,-19.55],"type":"Point"}
}