{
  "type": "Feature",
  "properties": {
    "gn:admin1_code":"18.0",
    "gn:asciiname":"Mere",
    "gn:country_code":"VU",
    "gn:dem":272,
    "gn:feature_class":"P",
    "gn:feature_code":"PPL",
    "gn:name":"M\u00e9r\u00e9",
    "gn:population":0,
    "gn:timezone":"Pacific/Efate",
    "iso:country":"VU",
    "name:ceb_x_preferred":[
        "Mere"
    ],
    "name:deu_x_preferred":[
        "Mere"
    ],
    "name:est_x_preferred":[
        "Mere"
    ],
    "name:ita_x_preferred":[
        "Mere"
    ],
    "name:nds_x_preferred":[
        "Mere"
    ],
    "name:nld_x_preferred":[
        "Mere"
    ],
    "name:pol_x_preferred":[
        "Mere"
    ],
    "name:rus_x_preferred":[
        "\u041c\u0435\u0440\u0435"
    ],
    "name:swe_x_preferred":[
        "Mere"
    ],
    "name:ukr_x_preferred":[
        "\u041c\u0435\u0440\u0435"
    ],
    "wof:name":"Mere",
    "wof:placetype":"locality"
},
  "geometry": {"coordinates":[168.36667,-17.46667],"type":"Point"}
}