{
  "type": "Feature",
  "properties": {
    "gn:admin1_code":"18.0",
    "gn:asciiname":"Mere",
    "gn:country_code":"VU",
    "gn:dem":272,
    "gn:feature_class":"P",
    "gn:feature_code":"PPL",
    "gn:name":"M\u00e9r\u00e9",
    "gn:population":0,
    "gn:timezone":"Pacific/Efate",
    "iso:country":"VU",
    "wof:name":"Mere",
    "wof:placetype":"locality"
},
  "geometry": {"coordinates":[168.36667,-17.46667],"type":"Point"}
}