{
  "type": "Feature",
  "properties": {
    "gn:admin1_code":"17.0",
    "gn:asciiname":"Ranwas",
    "gn:country_code":"VU",
    "gn:dem":429,
    "gn:feature_class":"P",
    "gn:feature_code":"PPL",
    "gn:name":"Ranwas",
    "gn:population":0,
    "gn:timezone":"Pacific/Efate",
    "iso:country":"VU",
    "wof:name":"Ranwas",
    "wof:placetype":"locality"
},
  "geometry": {"coordinates":[168.25,-15.96667],"type":"Point"}
}