{
  "type": "Feature",
  "properties": {
    "gn:admin1_code":"15.0",
    "gn:asciiname":"Rampounrougou",
    "gn:country_code":"VU",
    "gn:dem":232,
    "gn:feature_class":"P",
    "gn:feature_code":"PPL",
    "gn:name":"Rampounrougou",
    "gn:population":0,
    "gn:timezone":"Pacific/Efate",
    "iso:country":"VU",
    "wof:name":"Rampounrougou",
    "wof:placetype":"locality"
},
  "geometry": {"coordinates":[169.08333000000005,-18.91667],"type":"Point"}
}