{
  "type": "Feature",
  "properties": {
    "gn:admin1_code":"18.0",
    "gn:asciiname":"Port-Havannah",
    "gn:country_code":"VU",
    "gn:dem":0,
    "gn:feature_class":"P",
    "gn:feature_code":"PPL",
    "gn:name":"Port-Havannah",
    "gn:population":0,
    "gn:timezone":"Pacific/Efate",
    "iso:country":"VU",
    "wof:name":"Port-Havannah",
    "wof:placetype":"locality"
},
  "geometry": {"coordinates":[168.27222,-17.56667],"type":"Point"}
}