{
  "type": "Feature",
  "properties": {
    "gn:admin1_code":"17.0",
    "gn:asciiname":"Bounlap",
    "gn:country_code":"VU",
    "gn:dem":91,
    "gn:feature_class":"P",
    "gn:feature_code":"PPL",
    "gn:name":"Bounlap",
    "gn:population":0,
    "gn:timezone":"Pacific/Efate",
    "iso:country":"VU",
    "name:rus_x_preferred":[
        "\u0411\u0443\u043d\u043b\u0430\u043f"
    ],
    "name:und_x_variant":[
        "Bunlap",
        "Bounlap"
    ],
    "wof:name":"Bounlap",
    "wof:placetype":"locality"
},
  "geometry": {"coordinates":[168.26667,-15.96667],"type":"Point"}
}