{
  "type": "Feature",
  "properties": {
    "gn:admin1_code":"15.0",
    "gn:asciiname":"Loweao",
    "gn:cc2":"VU",
    "gn:country_code":"VU",
    "gn:dem":318,
    "gn:feature_class":"P",
    "gn:feature_code":"PPL",
    "gn:name":"Low\u00e9ao",
    "gn:population":0,
    "gn:timezone":"Pacific/Efate",
    "iso:country":"VU",
    "name:und_x_variant":[
        "Loviarou",
        "Low\u00e9ao"
    ],
    "wof:name":"Loweao",
    "wof:placetype":"locality"
},
  "geometry": {"coordinates":[169.30000000000001,-19.45],"type":"Point"}
}