{
  "type": "Feature",
  "properties": {
    "gn:admin1_code":"16.0",
    "gn:asciiname":"Holen",
    "gn:country_code":"VU",
    "gn:dem":55,
    "gn:feature_class":"P",
    "gn:feature_code":"PPL",
    "gn:name":"Holen",
    "gn:population":0,
    "gn:timezone":"Pacific/Efate",
    "iso:country":"VU",
    "wof:name":"Holen",
    "wof:placetype":"locality"
},
  "geometry": {"coordinates":[168.31666999999999,-16.51667],"type":"Point"}
}