{
  "type": "Feature",
  "properties": {
    "gn:admin1_code":"17.0",
    "gn:asciiname":"Lamorou",
    "gn:country_code":"VU",
    "gn:dem":-9999,
    "gn:feature_class":"P",
    "gn:feature_code":"PPL",
    "gn:name":"Lamorou",
    "gn:population":0,
    "gn:timezone":"Pacific/Efate",
    "iso:country":"VU",
    "wof:name":"Lamorou",
    "wof:placetype":"locality"
},
  "geometry": {"coordinates":[168.13333,-15.46667],"type":"Point"}
}