{
  "type": "Feature",
  "properties": {
    "gn:admin1_code":"13.0",
    "gn:asciiname":"Pakapoultol",
    "gn:country_code":"VU",
    "gn:dem":178,
    "gn:feature_class":"P",
    "gn:feature_code":"PPL",
    "gn:name":"Pakapoultol",
    "gn:population":0,
    "gn:timezone":"Pacific/Efate",
    "iso:country":"VU",
    "wof:name":"Pakapoultol",
    "wof:placetype":"locality"
},
  "geometry": {"coordinates":[166.80000000000001,-15.63333],"type":"Point"}
}