{
  "type": "Feature",
  "properties": {
    "gn:country":"VU",
    "gn:fcode":"PPL",
    "gn:population":1171,
    "iso:country":"VU",
    "name:bel_x_preferred":[
        "\u0413\u043e\u0440\u0430\u0434 \u0421\u043e\u043b\u0430"
    ],
    "name:bis_x_preferred":[
        "Sola"
    ],
    "name:cat_x_preferred":[
        "Sola"
    ],
    "name:ceb_x_preferred":[
        "Sola"
    ],
    "name:deu_x_preferred":[
        "Sola"
    ],
    "name:eng_x_preferred":[
        "Sola"
    ],
    "name:fra_x_preferred":[
        "Sola"
    ],
    "name:glg_x_preferred":[
        "Sola"
    ],
    "name:hrv_x_preferred":[
        "Sola"
    ],
    "name:ita_x_preferred":[
        "Sola"
    ],
    "name:jpn_x_preferred":[
        "\u30bd\u30e9"
    ],
    "name:mrj_x_preferred":[
        "\u0421\u043e\u043b\u0430"
    ],
    "name:nld_x_preferred":[
        "Sola"
    ],
    "name:pol_x_preferred":[
        "Sola"
    ],
    "name:por_x_preferred":[
        "Sola"
    ],
    "name:rus_x_preferred":[
        "\u0421\u043e\u043b\u0430"
    ],
    "name:spa_x_preferred":[
        "Sola"
    ],
    "name:vep_x_preferred":[
        "Sol"
    ],
    "qs:name":"Sola",
    "qs:photos_9r":0,
    "qs:photos_sr":0,
    "qs:pop_sr":"3",
    "wd:wordcount":811,
    "wof:name":"Sola",
    "wof:placetype":"locality",
    "wof:population":1171
},
  "geometry": {"coordinates":[167.55000000000001,-13.88333],"type":"Point"}
}