{
  "type": "Feature",
  "properties": {
    "gn:admin1_code":"13.0",
    "gn:asciiname":"Lapourepoure",
    "gn:country_code":"VU",
    "gn:dem":1486,
    "gn:feature_class":"P",
    "gn:feature_code":"PPL",
    "gn:name":"Lapour\u00e9pour\u00e9",
    "gn:population":0,
    "gn:timezone":"Pacific/Efate",
    "iso:country":"VU",
    "wof:name":"Lapourepoure",
    "wof:placetype":"locality"
},
  "geometry": {"coordinates":[166.80000000000001,-15.43333],"type":"Point"}
}