{
  "type": "Feature",
  "properties": {
    "gn:admin1_code":"17.0",
    "gn:asciiname":"Saranamoundou",
    "gn:country_code":"VU",
    "gn:dem":155,
    "gn:feature_class":"P",
    "gn:feature_code":"PPL",
    "gn:name":"Saranamoundou",
    "gn:population":0,
    "gn:timezone":"Pacific/Efate",
    "iso:country":"VU",
    "wof:name":"Saranamoundou",
    "wof:placetype":"locality"
},
  "geometry": {"coordinates":[167.76667,-15.36667],"type":"Point"}
}