{
  "type": "Feature",
  "properties": {
    "gn:admin1_code":"13.0",
    "gn:asciiname":"Loarou",
    "gn:country_code":"VU",
    "gn:dem":181,
    "gn:feature_class":"P",
    "gn:feature_code":"PPL",
    "gn:name":"Loarou",
    "gn:population":0,
    "gn:timezone":"Pacific/Efate",
    "iso:country":"VU",
    "wof:name":"Loarou",
    "wof:placetype":"locality"
},
  "geometry": {"coordinates":[167.09999999999999,-15.16667],"type":"Point"}
}