{
  "type": "Feature",
  "properties": {
    "gn:admin1_code":"15.0",
    "gn:asciiname":"Imwafeun",
    "gn:country_code":"VU",
    "gn:dem":293,
    "gn:feature_class":"P",
    "gn:feature_code":"PPL",
    "gn:name":"Imwafeun",
    "gn:population":0,
    "gn:timezone":"Pacific/Efate",
    "iso:country":"VU",
    "wof:name":"Imwafeun",
    "wof:placetype":"locality"
},
  "geometry": {"coordinates":[169.28333000000001,-19.35],"type":"Point"}
}