{
  "type": "Feature",
  "properties": {
    "gn:admin1_code":"16.0",
    "gn:asciiname":"Nountor",
    "gn:country_code":"VU",
    "gn:dem":43,
    "gn:feature_class":"P",
    "gn:feature_code":"PPL",
    "gn:name":"Nountor",
    "gn:population":0,
    "gn:timezone":"Pacific/Efate",
    "iso:country":"VU",
    "wof:name":"Nountor",
    "wof:placetype":"locality"
},
  "geometry": {"coordinates":[168.11667,-16.15],"type":"Point"}
}