{
  "type": "Feature",
  "properties": {
    "gn:admin1_code":"16.0",
    "gn:asciiname":"Lonwel",
    "gn:country_code":"VU",
    "gn:dem":83,
    "gn:feature_class":"P",
    "gn:feature_code":"PPL",
    "gn:name":"Lonwel",
    "gn:population":0,
    "gn:timezone":"Pacific/Efate",
    "iso:country":"VU",
    "wof:name":"Lonwel",
    "wof:placetype":"locality"
},
  "geometry": {"coordinates":[168.09999999999999,-16.16667],"type":"Point"}
}