{
  "type": "Feature",
  "properties": {
    "gn:admin1_code":"0.0",
    "gn:asciiname":"Wormet",
    "gn:country_code":"VU",
    "gn:dem":75,
    "gn:feature_class":"P",
    "gn:feature_code":"PPL",
    "gn:name":"Wormet",
    "gn:population":0,
    "gn:timezone":"Pacific/Efate",
    "iso:country":"VU",
    "wof:name":"Wormet",
    "wof:placetype":"locality"
},
  "geometry": {"coordinates":[167.31994,-15.96351],"type":"Point"}
}