{
  "type": "Feature",
  "properties": {
    "gn:admin1_code":"15.0",
    "gn:asciiname":"Lamoueneuvel",
    "gn:country_code":"VU",
    "gn:dem":353,
    "gn:feature_class":"P",
    "gn:feature_code":"PPL",
    "gn:name":"Lamou\u00e9neuvel",
    "gn:population":0,
    "gn:timezone":"Pacific/Efate",
    "iso:country":"VU",
    "wof:name":"Lamoueneuvel",
    "wof:placetype":"locality"
},
  "geometry": {"coordinates":[169.30000000000001,-19.46667],"type":"Point"}
}