{
  "type": "Feature",
  "properties": {
    "gn:admin1_code":"13.0",
    "gn:asciiname":"Tolomako",
    "gn:cc2":"VU",
    "gn:country_code":"VU",
    "gn:dem":31,
    "gn:feature_class":"P",
    "gn:feature_code":"PPL",
    "gn:name":"Tolomako",
    "gn:population":0,
    "gn:timezone":"Pacific/Efate",
    "iso:country":"VU",
    "name:und_x_variant":[
        "Talomaco",
        "Talomako",
        "Tolomako"
    ],
    "wof:name":"Tolomako",
    "wof:placetype":"locality"
},
  "geometry": {"coordinates":[166.81666999999999,-15.16667],"type":"Point"}
}