{
  "type": "Feature",
  "properties": {
    "gn:admin1_code":"13.0",
    "gn:asciiname":"Natourouk",
    "gn:country_code":"VU",
    "gn:dem":532,
    "gn:feature_class":"P",
    "gn:feature_code":"PPL",
    "gn:name":"Natourouk",
    "gn:population":0,
    "gn:timezone":"Pacific/Efate",
    "iso:country":"VU",
    "wof:name":"Natourouk",
    "wof:placetype":"locality"
},
  "geometry": {"coordinates":[167.01667,-15.41667],"type":"Point"}
}