{
  "type": "Feature",
  "properties": {
    "gn:admin1_code":"16.0",
    "gn:asciiname":"Poutoumiel",
    "gn:country_code":"VU",
    "gn:dem":86,
    "gn:feature_class":"P",
    "gn:feature_code":"PPL",
    "gn:name":"Poutoumiel",
    "gn:population":0,
    "gn:timezone":"Pacific/Efate",
    "iso:country":"VU",
    "wof:name":"Poutoumiel",
    "wof:placetype":"locality"
},
  "geometry": {"coordinates":[167.16666999999995,-16.03333],"type":"Point"}
}