{
  "type": "Feature",
  "properties": {
    "gn:admin1_code":"13.0",
    "gn:asciiname":"Nokuku",
    "gn:country_code":"VU",
    "gn:dem":272,
    "gn:feature_class":"P",
    "gn:feature_code":"PPL",
    "gn:name":"Nokuku",
    "gn:population":0,
    "gn:timezone":"Pacific/Efate",
    "iso:country":"VU",
    "wof:name":"Nokuku",
    "wof:placetype":"locality"
},
  "geometry": {"coordinates":[166.56666999999999,-14.93333],"type":"Point"}
}