{
  "type": "Feature",
  "properties": {
    "gn:admin1_code":"13.0",
    "gn:asciiname":"Port Lautour",
    "gn:country_code":"VU",
    "gn:dem":-9999,
    "gn:feature_class":"P",
    "gn:feature_code":"PPL",
    "gn:name":"Port Lautour",
    "gn:population":0,
    "gn:timezone":"Pacific/Efate",
    "iso:country":"VU",
    "wof:name":"Port Lautour",
    "wof:placetype":"locality"
},
  "geometry": {"coordinates":[167.16666999999995,-15.61667],"type":"Point"}
}