{
  "type": "Feature",
  "properties": {
    "gn:admin1_code":"16.0",
    "gn:asciiname":"Yaotilie",
    "gn:country_code":"VU",
    "gn:dem":94,
    "gn:feature_class":"P",
    "gn:feature_code":"PPL",
    "gn:name":"Yaotilie",
    "gn:population":0,
    "gn:timezone":"Pacific/Efate",
    "iso:country":"VU",
    "wof:name":"Yaotilie",
    "wof:placetype":"locality"
},
  "geometry": {"coordinates":[167.99392,-16.28751],"type":"Point"}
}