{
  "type": "Feature",
  "properties": {
    "gn:admin1_code":"13.0",
    "gn:asciiname":"Pakaroro",
    "gn:country_code":"VU",
    "gn:dem":437,
    "gn:feature_class":"P",
    "gn:feature_code":"PPL",
    "gn:name":"Pakaroro",
    "gn:population":0,
    "gn:timezone":"Pacific/Efate",
    "iso:country":"VU",
    "wof:name":"Pakaroro",
    "wof:placetype":"locality"
},
  "geometry": {"coordinates":[166.66666999999995,-15.23333],"type":"Point"}
}