{
  "type": "Feature",
  "properties": {
    "gn:admin1_code":"7.0",
    "gn:asciiname":"Kerepoua",
    "gn:country_code":"VU",
    "gn:dem":-9999,
    "gn:feature_class":"P",
    "gn:feature_code":"PPL",
    "gn:name":"K\u00e9r\u00e9poua",
    "gn:population":0,
    "gn:timezone":"Pacific/Efate",
    "iso:country":"VU",
    "wof:name":"Kerepoua",
    "wof:placetype":"locality"
},
  "geometry": {"coordinates":[167.58333000000005,-13.88333],"type":"Point"}
}