{
  "type": "Feature",
  "properties": {
    "gn:admin1_code":"16.0",
    "gn:asciiname":"Falimapkon",
    "gn:country_code":"VU",
    "gn:dem":14,
    "gn:feature_class":"P",
    "gn:feature_code":"PPL",
    "gn:name":"Falimapkon",
    "gn:population":0,
    "gn:timezone":"Pacific/Efate",
    "iso:country":"VU",
    "wof:name":"Falimapkon",
    "wof:placetype":"locality"
},
  "geometry": {"coordinates":[167.91666999999995,-16.26667],"type":"Point"}
}