{
  "type": "Feature",
  "properties": {
    "gn:admin1_code":"18.0",
    "gn:asciiname":"Tafia",
    "gn:country_code":"VU",
    "gn:dem":20,
    "gn:feature_class":"P",
    "gn:feature_code":"PPL",
    "gn:name":"Tafia",
    "gn:population":0,
    "gn:timezone":"Pacific/Efate",
    "iso:country":"VU",
    "name:pol_x_preferred":[
        "Tafia"
    ],
    "wof:name":"Tafia",
    "wof:placetype":"locality"
},
  "geometry": {"coordinates":[168.61667,-17.01667],"type":"Point"}
}