{
  "type": "Feature",
  "properties": {
    "gn:admin1_code":"7.0",
    "gn:asciiname":"Viei",
    "gn:country_code":"VU",
    "gn:dem":1,
    "gn:feature_class":"P",
    "gn:feature_code":"PPL",
    "gn:name":"Viei",
    "gn:population":0,
    "gn:timezone":"Pacific/Efate",
    "iso:country":"VU",
    "wof:name":"Viei",
    "wof:placetype":"locality"
},
  "geometry": {"coordinates":[167.63333,-13.68333],"type":"Point"}
}