{
  "type": "Feature",
  "properties": {
    "gn:admin1_code":"16.0",
    "gn:asciiname":"Falibeur",
    "gn:country_code":"VU",
    "gn:dem":181,
    "gn:feature_class":"P",
    "gn:feature_code":"PPL",
    "gn:name":"Falibeur",
    "gn:population":0,
    "gn:timezone":"Pacific/Efate",
    "iso:country":"VU",
    "wof:name":"Falibeur",
    "wof:placetype":"locality"
},
  "geometry": {"coordinates":[168.16666999999995,-16.11667000000001],"type":"Point"}
}