{
  "type": "Feature",
  "properties": {
    "gn:admin1_code":"13.0",
    "gn:asciiname":"Elia",
    "gn:country_code":"VU",
    "gn:dem":16,
    "gn:feature_class":"P",
    "gn:feature_code":"PPL",
    "gn:name":"Elia",
    "gn:population":0,
    "gn:timezone":"Pacific/Efate",
    "iso:country":"VU",
    "wof:name":"Elia",
    "wof:placetype":"locality"
},
  "geometry": {"coordinates":[166.67410000000001,-15.2668],"type":"Point"}
}