{
  "type": "Feature",
  "properties": {
    "gn:admin1_code":"18.0",
    "gn:asciiname":"Moeriou",
    "gn:country_code":"VU",
    "gn:dem":46,
    "gn:feature_class":"P",
    "gn:feature_code":"PPL",
    "gn:name":"Mo\u00e9riou",
    "gn:population":0,
    "gn:timezone":"Pacific/Efate",
    "iso:country":"VU",
    "wof:name":"Moeriou",
    "wof:placetype":"locality"
},
  "geometry": {"coordinates":[168.55000000000001,-16.93333],"type":"Point"}
}