{
  "type": "Feature",
  "properties": {
    "gn:admin1_code":"13.0",
    "gn:asciiname":"Fwimatal",
    "gn:country_code":"VU",
    "gn:dem":425,
    "gn:feature_class":"P",
    "gn:feature_code":"PPL",
    "gn:name":"Fwimatal",
    "gn:population":0,
    "gn:timezone":"Pacific/Efate",
    "iso:country":"VU",
    "wof:name":"Fwimatal",
    "wof:placetype":"locality"
},
  "geometry": {"coordinates":[167.03333000000001,-15.45],"type":"Point"}
}