{
  "type": "Feature",
  "properties": {
    "gn:admin1_code":"15.0",
    "gn:asciiname":"Ipeukel",
    "gn:cc2":"VU",
    "gn:country_code":"VU",
    "gn:dem":58,
    "gn:feature_class":"P",
    "gn:feature_code":"PPL",
    "gn:name":"Ipeukel",
    "gn:population":0,
    "gn:timezone":"Pacific/Efate",
    "iso:country":"VU",
    "name:und_x_variant":[
        "Ipeukeul",
        "Ipeukel"
    ],
    "wof:name":"Ipeukel",
    "wof:placetype":"locality"
},
  "geometry": {"coordinates":[169.44999999999999,-19.51667],"type":"Point"}
}