{
  "type": "Feature",
  "properties": {
    "gn:admin1_code":"17.0",
    "gn:asciiname":"Nokongiri",
    "gn:country_code":"VU",
    "gn:dem":447,
    "gn:feature_class":"P",
    "gn:feature_code":"PPL",
    "gn:name":"Nokongiri",
    "gn:population":0,
    "gn:timezone":"Pacific/Efate",
    "iso:country":"VU",
    "wof:name":"Nokongiri",
    "wof:placetype":"locality"
},
  "geometry": {"coordinates":[168.18333000000001,-15.66667],"type":"Point"}
}