{
  "type": "Feature",
  "properties": {
    "gn:admin1_code":"15.0",
    "gn:asciiname":"Enfitana",
    "gn:country_code":"VU",
    "gn:dem":355,
    "gn:feature_class":"P",
    "gn:feature_code":"PPL",
    "gn:name":"Enfitana",
    "gn:population":0,
    "gn:timezone":"Pacific/Efate",
    "iso:country":"VU",
    "wof:name":"Enfitana",
    "wof:placetype":"locality"
},
  "geometry": {"coordinates":[169.34999999999999,-19.58333],"type":"Point"}
}