{
  "type": "Feature",
  "properties": {
    "gn:admin1_code":"7.0",
    "gn:asciiname":"Vatles",
    "gn:country_code":"VU",
    "gn:dem":470,
    "gn:feature_class":"P",
    "gn:feature_code":"PPL",
    "gn:name":"Vatl\u00e9s",
    "gn:population":0,
    "gn:timezone":"Pacific/Efate",
    "iso:country":"VU",
    "wof:name":"Vatles",
    "wof:placetype":"locality"
},
  "geometry": {"coordinates":[167.44999999999999,-14.21667],"type":"Point"}
}