{
  "type": "Feature",
  "properties": {
    "gn:admin1_code":"16.0",
    "gn:asciiname":"Loluerkon",
    "gn:country_code":"VU",
    "gn:dem":51,
    "gn:feature_class":"P",
    "gn:feature_code":"PPL",
    "gn:name":"Loluerkon",
    "gn:population":0,
    "gn:timezone":"Pacific/Efate",
    "iso:country":"VU",
    "wof:name":"Loluerkon",
    "wof:placetype":"locality"
},
  "geometry": {"coordinates":[168.08333000000005,-16.16667],"type":"Point"}
}