{
  "type": "Feature",
  "properties": {
    "gn:admin1_code":"13.0",
    "gn:asciiname":"Benavoue",
    "gn:country_code":"VU",
    "gn:dem":52,
    "gn:feature_class":"P",
    "gn:feature_code":"PPL",
    "gn:name":"B\u00e9navou\u00e9",
    "gn:population":0,
    "gn:timezone":"Pacific/Efate",
    "iso:country":"VU",
    "wof:name":"Benavoue",
    "wof:placetype":"locality"
},
  "geometry": {"coordinates":[167.03333000000001,-15.58333],"type":"Point"}
}