{
  "type": "Feature",
  "properties": {
    "gn:admin1_code":"13.0",
    "gn:asciiname":"Wusi",
    "gn:cc2":"VU",
    "gn:country_code":"VU",
    "gn:dem":581,
    "gn:feature_class":"P",
    "gn:feature_code":"PPL",
    "gn:name":"Wusi",
    "gn:population":0,
    "gn:timezone":"Pacific/Efate",
    "iso:country":"VU",
    "name:und_x_variant":[
        "Poussy",
        "Wus",
        "Wousi",
        "Wusi"
    ],
    "wof:name":"Wusi",
    "wof:placetype":"locality"
},
  "geometry": {"coordinates":[166.65000000000001,-15.36667],"type":"Point"}
}