{
  "type": "Feature",
  "properties": {
    "gn:admin1_code":"13.0",
    "gn:asciiname":"Worovok",
    "gn:country_code":"VU",
    "gn:dem":36,
    "gn:feature_class":"P",
    "gn:feature_code":"PPL",
    "gn:name":"Worovok",
    "gn:population":0,
    "gn:timezone":"Pacific/Efate",
    "iso:country":"VU",
    "wof:name":"Worovok",
    "wof:placetype":"locality"
},
  "geometry": {"coordinates":[166.88333,-15.18333],"type":"Point"}
}