{
  "type": "Feature",
  "properties": {
    "gn:asciiname":"Telvet",
    "gn:country_code":"VU",
    "gn:dem":31,
    "gn:feature_class":"P",
    "gn:feature_code":"PPL",
    "gn:name":"Telvet",
    "gn:population":0,
    "gn:timezone":"Pacific/Efate",
    "iso:country":"VU",
    "wof:name":"Telvet",
    "wof:placetype":"locality"
},
  "geometry": {"coordinates":[167.70670000000001,-13.65452],"type":"Point"}
}