{
  "type": "Feature",
  "properties": {
    "gn:admin1_code":"18.0",
    "gn:asciiname":"Bosao",
    "gn:country_code":"VU",
    "gn:dem":54,
    "gn:feature_class":"P",
    "gn:feature_code":"PPL",
    "gn:name":"Bosao",
    "gn:population":0,
    "gn:timezone":"Pacific/Efate",
    "iso:country":"VU",
    "wof:name":"Bosao",
    "wof:placetype":"locality"
},
  "geometry": {"coordinates":[168.18333000000001,-16.78333],"type":"Point"}
}