{
  "type": "Feature",
  "properties": {
    "gn:admin1_code":"18.0",
    "gn:asciiname":"Welawea",
    "gn:country_code":"VU",
    "gn:dem":7,
    "gn:feature_class":"P",
    "gn:feature_code":"PPL",
    "gn:name":"W\u00e9law\u00e9a",
    "gn:population":0,
    "gn:timezone":"Pacific/Efate",
    "iso:country":"VU",
    "wof:name":"Welawea",
    "wof:placetype":"locality"
},
  "geometry": {"coordinates":[168.15000000000001,-16.61667000000001],"type":"Point"}
}