{
  "type": "Feature",
  "properties": {
    "gn:admin1_code":"0.0",
    "gn:asciiname":"Melerep",
    "gn:country_code":"VU",
    "gn:dem":184,
    "gn:feature_class":"P",
    "gn:feature_code":"PPL",
    "gn:name":"Melerep",
    "gn:population":0,
    "gn:timezone":"Pacific/Efate",
    "iso:country":"VU",
    "wof:name":"Melerep",
    "wof:placetype":"locality"
},
  "geometry": {"coordinates":[168.13588999999999,-15.61821],"type":"Point"}
}