{
  "type": "Feature",
  "properties": {
    "gn:admin1_code":"17.0",
    "gn:asciiname":"Wousounmwel",
    "gn:country_code":"VU",
    "gn:dem":397,
    "gn:feature_class":"P",
    "gn:feature_code":"PPL",
    "gn:name":"Wousounmw\u00e8l",
    "gn:population":0,
    "gn:timezone":"Pacific/Efate",
    "iso:country":"VU",
    "wof:name":"Wousounmwel",
    "wof:placetype":"locality"
},
  "geometry": {"coordinates":[168.16666999999995,-15.68333],"type":"Point"}
}