{
  "type": "Feature",
  "properties": {
    "gn:admin1_code":"7.0",
    "gn:asciiname":"Tarasag",
    "gn:country_code":"VU",
    "gn:dem":108,
    "gn:feature_class":"P",
    "gn:feature_code":"PPL",
    "gn:name":"Tarasag",
    "gn:population":0,
    "gn:timezone":"Pacific/Efate",
    "iso:country":"VU",
    "wof:name":"Tarasag",
    "wof:placetype":"locality"
},
  "geometry": {"coordinates":[167.58333000000005,-14.25],"type":"Point"}
}