{
  "type": "Feature",
  "properties": {
    "gn:admin1_code":"17.0",
    "gn:asciiname":"Lavonda",
    "gn:country_code":"VU",
    "gn:dem":27,
    "gn:feature_class":"P",
    "gn:feature_code":"PPL",
    "gn:name":"Lavonda",
    "gn:population":0,
    "gn:timezone":"Pacific/Efate",
    "iso:country":"VU",
    "wof:name":"Lavonda",
    "wof:placetype":"locality"
},
  "geometry": {"coordinates":[167.94999999999999,-15.35],"type":"Point"}
}