{
  "type": "Feature",
  "properties": {
    "gn:admin1_code":"18.0",
    "gn:asciiname":"Ounakop",
    "gn:country_code":"VU",
    "gn:dem":13,
    "gn:feature_class":"P",
    "gn:feature_code":"PPL",
    "gn:name":"Ounakop",
    "gn:population":0,
    "gn:timezone":"Pacific/Efate",
    "iso:country":"VU",
    "name:und_x_variant":[
        "Taoloa",
        "Ounakop"
    ],
    "wof:name":"Ounakop",
    "wof:placetype":"locality"
},
  "geometry": {"coordinates":[168.38333,-17.48333],"type":"Point"}
}