{
  "type": "Feature",
  "properties": {
    "gn:admin1_code":"13.0",
    "gn:asciiname":"Atsoma",
    "gn:country_code":"VU",
    "gn:dem":1029,
    "gn:feature_class":"P",
    "gn:feature_code":"PPL",
    "gn:name":"Atsoma",
    "gn:population":0,
    "gn:timezone":"Pacific/Efate",
    "iso:country":"VU",
    "wof:name":"Atsoma",
    "wof:placetype":"locality"
},
  "geometry": {"coordinates":[166.75,-15.46667],"type":"Point"}
}