{
  "type": "Feature",
  "properties": {
    "gn:asciiname":"umpon Mompu",
    "gn:country_code":"VU",
    "gn:dem":268,
    "gn:feature_class":"P",
    "gn:feature_code":"PPL",
    "gn:name":"umpon Mompu",
    "gn:population":0,
    "gn:timezone":"Pacific/Efate",
    "iso:country":"VU",
    "wof:name":"umpon Mompu",
    "wof:placetype":"locality"
},
  "geometry": {"coordinates":[169.14388,-18.92577],"type":"Point"}
}